{
  "last_update": "2025-12-23T14:19:42.703343",
  "today_profit": 0,
  "today_profit_percent": 0.0,
  "total_profit": 0,
  "total_profit_percent": 0.0,
  "total_investment": 75474.6502319132,
  "holdings": [
    {
      "market": "KRW-CHR",
      "amount": 335.18145161,
      "avg_price": 58.3,
      "current_price": 58.3,
      "value": 19541.078628863,
      "profit": 0.0,
      "profit_rate": 0.0
    },
    {
      "market": "KRW-GHX",
      "amount": 1982.06715112,
      "avg_price": 18.37,
      "current_price": 17.95,
      "value": 35578.105362604,
      "profit": -832.4682034704034,
      "profit_rate": -0.022863364180729543
    },
    {
      "market": "KRW-BLY",
      "amount": 3810.16042781,
      "avg_price": 2.56,
      "current_price": 2.565,
      "value": 9773.06149733265,
      "profit": 19.050802139049594,
      "profit_rate": 0.0019531249999999584
    },
    {
      "market": "KRW-AZIT",
      "amount": 1107.59493671,
      "avg_price": 8.82,
      "current_price": 8.752,
      "value": 9693.67088608592,
      "profit": -75.31645569627958,
      "profit_rate": -0.00770975056689338
    }
  ],
  "trades": [],
  "daily_profits": {},
  "trade_cycles": [],
  "start_date": "2025-12-23"
}