{
  "last_update": "2025-12-23T10:39:25.795295",
  "today_profit": 0,
  "today_profit_percent": 0.0,
  "total_profit": 0,
  "total_profit_percent": 0.0,
  "total_investment": 101508.68531236,
  "holdings": [
    {
      "market": "KRW-COMP",
      "amount": 1.92742108,
      "avg_price": 35759.0,
      "current_price": 36440.0,
      "value": 70235.2241552,
      "profit": 1312.57375548,
      "profit_rate": 0.019044156715791828
    },
    {
      "market": "KRW-SAPIEN",
      "amount": 185.14792564,
      "avg_price": 176.0,
      "current_price": 176.0,
      "value": 32586.034912640003,
      "profit": 0.0,
      "profit_rate": 0.0
    }
  ],
  "trades": [],
  "daily_profits": {},
  "trade_cycles": [],
  "start_date": "2025-12-23"
}