{
  "last_update": "2025-12-23T22:48:47.726274",
  "today_profit": 0,
  "today_profit_percent": 0.0,
  "total_profit": 0,
  "total_profit_percent": 0.0,
  "total_investment": 64194.6840894336,
  "holdings": [
    {
      "market": "KRW-BTC",
      "amount": 8.994e-05,
      "avg_price": 130426000.0,
      "current_price": 130646000.0,
      "value": 11750.301239999999,
      "profit": 19.7868,
      "profit_rate": 0.0016867802432030423
    },
    {
      "market": "KRW-ETH",
      "amount": 0.00398204,
      "avg_price": 4418000.0,
      "current_price": 4394000.0,
      "value": 17497.08376,
      "profit": -95.56896,
      "profit_rate": -0.005432322317790856
    },
    {
      "market": "KRW-BLY",
      "amount": 3810.16042781,
      "avg_price": 2.56,
      "current_price": 2.566,
      "value": 9776.87165776046,
      "profit": 22.860962566859172,
      "profit_rate": 0.0023437499999999153
    },
    {
      "market": "KRW-RESOLV",
      "amount": 224.26344852,
      "avg_price": 112.0,
      "current_price": 113.0,
      "value": 25341.76968276,
      "profit": 224.26344852,
      "profit_rate": 0.008928571428571428
    }
  ],
  "trades": [],
  "daily_profits": {},
  "trade_cycles": [],
  "start_date": "2025-12-23"
}